langchain_xinference/__init__.py
langchain_xinference/chat_models.py
langchain_xinference/embeddings.py
langchain_xinference/llms.py
langchain_xinference/py.typed
langchain_xinference/reranks.py
langchain_xinference-0.1.2.dist-info/LICENSE
langchain_xinference-0.1.2.dist-info/METADATA
langchain_xinference-0.1.2.dist-info/WHEEL
langchain_xinference-0.1.2.dist-info/RECORD
